<?xml version="1.0" encoding="UTF-8"?>
<beans xmlns="http://www.springframework.org/schema/beans" xmlns:xsi="http://www.w3.org/2001/XMLSchema-instance"
        xsi:schemaLocation="http://www.springframework.org/schema/beans
       http://www.springframework.org/schema/beans/spring-beans.xsd">

    <!--mvc:annotation-driven /-->

    <!-- Enable to request mappings PER METHOD -->
    <bean class="org.springframework.web.servlet.mvc.annotation.AnnotationMethodHandlerAdapter"/>

    <!-- Enable annotated POJO @Controller -->
    <bean class="org.springframework.web.servlet.mvc.annotation.DefaultAnnotationHandlerMapping"/>

    <bean id="propertyTestController" class="com.mikenimer.palladium.samples.controllers.PropertyTestController"/>



    <bean class="org.springframework.web.servlet.view.ContentNegotiatingViewResolver">
        <property name="mediaTypes">
            <map>
                <entry key="json" value="application/json" />
                <entry key="xml" value="application/xml" />
            </map>
        </property>
        <property name="defaultViews">
            <list>
                <bean class="org.springframework.web.servlet.view.json.MappingJacksonJsonView">
                </bean>

                <bean class="org.springframework.web.servlet.view.xml.MarshallingView">
                    <property name="marshaller">
                        <bean class="org.springframework.oxm.xstream.XStreamMarshaller">
                            <property name="autodetectAnnotations" value="true"/>
                            <property name="supportedClasses">
                                <list>
                                    <value>java.util.Collection</value>
                                    <value>java.util.HashMap</value>
                                </list>
                            </property>
                        </bean>
                    </property>
                </bean>
            </list>
        </property>
    </bean>



    <!-- Define the view resolver to use jsp files within the jsp folder -->
    <bean class="org.springframework.web.servlet.view.InternalResourceViewResolver">
        <property name="viewClass" value="com.mikenimer.palladium.spring.mvc.views.ColdFusionView" />
        <property name="prefix" value="/kitchensink-inf/views/propertytest-views/" />
        <property name="suffix" value=".cfm" />
        <property name="attributesMap">
            <map>
                <!-- properties to make java CF friendly -->
                <entry key="convertKeys" value="true"/>
                <entry key="lowerCaseKeys" value="true"/>
                <entry key="convertCollections" value="true"/>
                <entry key="convertNulls" value="true"/>
                <entry key="beans">
                    <map>
                         <entry key="propertyHelper">
                            <bean class="com.mikenimer.palladium.utils.PropertyHelper"/>
                        </entry>
                        <entry key="collectionHelper">
                            <bean class="com.mikenimer.palladium.utils.CollectionHelper"/>
                        </entry>
                    </map>
                </entry>
            </map>
        </property>
    </bean>

</beans>
